README.md
setup.cfg
setup.py
src/fdio/__init__.py
src/fdio/fdio.py
src/fdio/utils.py
src/fdio.egg-info/PKG-INFO
src/fdio.egg-info/SOURCES.txt
src/fdio.egg-info/dependency_links.txt
src/fdio.egg-info/entry_points.txt
src/fdio.egg-info/not-zip-safe
src/fdio.egg-info/requires.txt
src/fdio.egg-info/top_level.txt