Metadata-Version: 2.1
Name: fdio
Version: 1.1
Summary: A CLI tool that manages files and directories.
Home-page: https://github.com/ayoub-aberbach/fdio
Author: Ayoub A.
Author-email: aberbach.me@gmail.com
License: MIT
Keywords: cli,file,io
Classifier: Programming Language :: Python :: 3
Classifier: License :: OSI Approved :: MIT License
Requires-Python: >=3.6
Requires-Dist: importlib-metadata; python_version < "3.11"
